setupCMR.py
WRLC.egg-info/PKG-INFO
WRLC.egg-info/SOURCES.txt
WRLC.egg-info/dependency_links.txt
WRLC.egg-info/top_level.txt