Metadata-Version: 1.0
Name: WRLC
Version: 0.4
Summary: Runtime-level framework, subsystem, and language library.
Home-page: http://penobscotrobotics.us/cms/page/access-wrlc.htm
Author: Clint Banis
Author-email: UNKNOWN
License: none
Download-URL: True
Platform: OS-independent
Platform: Many
